picker/__init__.py
picker/exception.py
picker/repo.json
picker/settings.py
picker/test_settings.py
picker/static/picker/angularjs/angular.min.js
picker/static/picker/bootstrap/css/bootstrap-theme.css.map
picker/static/picker/bootstrap/css/bootstrap-theme.min.css
picker/static/picker/bootstrap/css/bootstrap.css.map
picker/static/picker/bootstrap/css/bootstrap.min.css
picker/static/picker/bootstrap/fonts/glyphicons-halflings-regular.eot
picker/static/picker/bootstrap/fonts/glyphicons-halflings-regular.svg
picker/static/picker/bootstrap/fonts/glyphicons-halflings-regular.ttf
picker/static/picker/bootstrap/fonts/glyphicons-halflings-regular.woff
picker/static/picker/bootstrap/fonts/glyphicons-halflings-regular.woff2
picker/static/picker/bootstrap/js/bootstrap.js
picker/static/picker/bootstrap/js/bootstrap.min.js
picker/static/picker/bootstrap/js/npm.js
picker/static/picker/bootstrap-cosmo/css/cosmo.min.css
picker/static/picker/bootstrap-cosmo/fonts/glyphicons-halflings-regular.eot
picker/static/picker/bootstrap-cosmo/fonts/glyphicons-halflings-regular.svg
picker/static/picker/bootstrap-cosmo/fonts/glyphicons-halflings-regular.ttf
picker/static/picker/bootstrap-cosmo/fonts/glyphicons-halflings-regular.woff
picker/static/picker/bootstrap-cosmo/fonts/glyphicons-halflings-regular.woff2
picker/static/picker/bootstrap4/css/bootstrap-grid.min.css
picker/static/picker/bootstrap4/css/bootstrap-reboot.min.css
picker/static/picker/bootstrap4/css/bootstrap.min.css
picker/static/picker/bootstrap4/js/bootstrap.bundle.min.js
picker/static/picker/bootstrap4/js/bootstrap.min.js
picker/static/picker/bootstrap4-darkly/css/bootstrap.min.css
picker/static/picker/bootstrap5/css/bootstrap.min.css
picker/static/picker/bootstrap5/js/bootstrap.bundle.min.js
picker/static/picker/ember/ember-1.5.1.js
picker/static/picker/ember/handlebars-1.1.2.js
picker/static/picker/fontawesome/css/all.min.css
picker/static/picker/fontawesome/webfonts/fa-brands-400.eot
django_picker-1.0.1.dist-info/METADATA
django_picker-1.0.1.dist-info/WHEEL
django_picker-1.0.1.dist-info/top_level.txt
django_picker-1.0.1.dist-info/RECORD
