Metadata-Version: 2.1
Name: django-picker
Version: 1.0.1
Summary: Put javascript, css framework into your project.
Home-page: http://github.com/shinznatkid/picker
Author: ShinZ Natkid
Author-email: shinznatkid@gmail.com
License: BSD
Classifier: Development Status :: 4 - Beta
Classifier: Programming Language :: Python :: 3.5
